dupesearch-0.1.13.dist-info/METADATA
dupesearch-0.1.13.dist-info/WHEEL
dupesearch/__main__.py
dupesearch/__init__.py
dupesearch/cli.py
dupesearch/dupesearch.cpython-39-x86_64-linux-gnu.so
dupesearch-0.1.13.dist-info/RECORD
