Metadata-Version: 2.1
Name: dupesearch
Version: 0.1.13
Classifier: Development Status :: 2 - Pre-Alpha
Classifier: Intended Audience :: End Users/Desktop
Classifier: Operating System :: MacOS
Classifier: Operating System :: Microsoft :: Windows
Classifier: Operating System :: POSIX :: Linux
Classifier: Programming Language :: Python :: 3
Classifier: Programming Language :: Python :: 3.7
Classifier: Programming Language :: Python :: 3.8
Classifier: Programming Language :: Python :: 3.9
Classifier: Programming Language :: Python
Classifier: Programming Language :: Rust
Classifier: Topic :: Utilities
Requires-Dist: click==8.*
Requires-Dist: rich==10.*
Summary: Remove duplicate files quickly with a simple command line tool
Author: wookie184 <wookie1840@gmail.com>
Author-email: wookie184 <wookie1840@gmail.com>
Project-URL: repository, https://github.com/wookie184/dupesearch
